[
  {
    "date": "2022-02-13",
    "apollo": "91,901,122.30"
  },
  {
    "date": "2022-02-14",
    "apollo": "109,441,509.37"
  },
  {
    "date": "2022-02-15",
    "apollo": "114,811,726.99"
  },
  {
    "date": "2022-02-16",
    "apollo": "126,872,511.18"
  },
  {
    "date": "2022-02-17",
    "apollo": "135,146,572.93"
  },
  {
    "date": "2022-02-18",
    "apollo": "137,344,820.78"
  },
  {
    "date": "2022-02-19",
    "apollo": "141,919,069.60"
  },
  {
    "date": "2022-02-20",
    "apollo": "160,420,836.80"
  },
  {
    "date": "2022-02-21",
    "apollo": "162,667,222.92"
  },
  {
    "date": "2022-02-22",
    "apollo": "174,815,002.34"
  },
  {
    "date": "2022-02-23",
    "apollo": "194,460,072.91"
  },
  {
    "date": "2022-02-24",
    "apollo": "242,491,912.81"
  },
  {
    "date": "2022-02-25",
    "apollo": "237,959,521.85"
  },
  {
    "date": "2022-02-26",
    "apollo": "239,269,664.26"
  },
  {
    "date": "2022-02-27",
    "apollo": "238,191,737.97"
  },
  {
    "date": "2022-02-28",
    "apollo": "234,109,998.01"
  },
  {
    "date": "2022-03-01",
    "apollo": "251,170,902.21"
  },
  {
    "date": "2022-03-02",
    "starlay": "26,416,724.34",
    "apollo": "249,723,593.07"
  },
  {
    "date": "2022-03-03",
    "starlay": "25,972,653.52",
    "apollo": "245,205,903.74"
  },
  {
    "date": "2022-03-04",
    "starlay": "25,919,555.65",
    "apollo": "247,025,467.88"
  },
  {
    "date": "2022-03-05",
    "starlay": "39,944,480.55",
    "apollo": "248,960,447.26"
  },
  {
    "date": "2022-03-06",
    "starlay": "40,979,185.71",
    "apollo": "258,340,198.31"
  },
  {
    "date": "2022-03-07",
    "starlay": "37,517,707.99",
    "apollo": "250,135,322.35"
  },
  {
    "date": "2022-03-08",
    "starlay": "40,829,097.18",
    "apollo": "253,579,035.59"
  },
  {
    "date": "2022-03-09",
    "starlay": "48,776,662.54",
    "apollo": "256,067,821.04"
  },
  {
    "date": "2022-03-10",
    "starlay": "59,360,802.95",
    "apollo": "255,657,907.74"
  },
  {
    "date": "2022-03-11",
    "starlay": "61,423,511.09",
    "apollo": "253,346,816.92"
  },
  {
    "date": "2022-03-12",
    "starlay": "62,060,797.11",
    "apollo": "251,317,053.39"
  },
  {
    "date": "2022-03-13",
    "starlay": "60,463,497.97",
    "apollo": "237,797,562.13"
  },
  {
    "date": "2022-03-14",
    "starlay": "60,222,505.43",
    "apollo": "232,868,765.53"
  },
  {
    "date": "2022-03-15",
    "starlay": "61,509,121.92",
    "apollo": "238,412,941.69"
  },
  {
    "date": "2022-03-16",
    "starlay": "61,989,628.17",
    "apollo": "239,252,927.03"
  },
  {
    "date": "2022-03-17",
    "starlay": "72,722,909.91",
    "apollo": "245,848,941.21"
  },
  {
    "date": "2022-03-18",
    "starlay": "80,922,707.94",
    "apollo": "244,988,620.93"
  },
  {
    "date": "2022-03-19",
    "starlay": "86,366,446.23",
    "apollo": "245,896,508.01"
  },
  {
    "date": "2022-03-20",
    "starlay": "88,427,440.33",
    "apollo": "249,981,158.09"
  },
  {
    "date": "2022-03-21",
    "starlay": "87,848,593.03",
    "apollo": "249,708,068.15"
  },
  {
    "date": "2022-03-22",
    "starlay": "94,025,203.68",
    "apollo": "262,640,480.31"
  },
  {
    "date": "2022-03-23",
    "starlay": "99,911,101.47",
    "apollo": "268,425,508.67"
  },
  {
    "date": "2022-03-24",
    "starlay": "100,884,570.92",
    "apollo": "274,858,812.15"
  },
  {
    "date": "2022-03-25",
    "starlay": "105,462,247.30",
    "apollo": "274,963,580.10"
  },
  {
    "date": "2022-03-26",
    "starlay": "105,212,699.50",
    "apollo": "276,036,797.72"
  },
  {
    "date": "2022-03-27",
    "starlay": "106,380,061.72",
    "apollo": "281,047,728.80"
  },
  {
    "date": "2022-03-28",
    "starlay": "114,610,725.67",
    "apollo": "287,764,706.30"
  },
  {
    "date": "2022-03-29",
    "starlay": "120,319,699.08",
    "apollo": "291,371,293.95"
  },
  {
    "date": "2022-03-30",
    "starlay": "122,774,738.70",
    "apollo": "301,152,356.73"
  },
  {
    "date": "2022-03-31",
    "starlay": "128,210,222.86",
    "apollo": "303,501,085.87"
  },
  {
    "date": "2022-04-01",
    "starlay": "132,277,641.80",
    "apollo": "302,002,065.39"
  },
  {
    "date": "2022-04-02",
    "starlay": "155,230,889.39",
    "apollo": "313,205,114.08"
  },
  {
    "date": "2022-04-03",
    "starlay": "163,397,150.46",
    "apollo": "319,186,807.78"
  },
  {
    "date": "2022-04-04",
    "starlay": "144,246,884.66",
    "apollo": "322,542,805.44"
  },
  {
    "date": "2022-04-05",
    "starlay": "154,526,906.68",
    "apollo": "344,980,369.48"
  },
  {
    "date": "2022-04-06",
    "starlay": "152,554,533.41",
    "apollo": "344,932,129.46"
  },
  {
    "date": "2022-04-07",
    "starlay": "149,236,376.43",
    "apollo": "335,631,327.93"
  },
  {
    "date": "2022-04-08",
    "starlay": "158,264,684.79",
    "apollo": "342,284,685.94"
  },
  {
    "date": "2022-04-09",
    "starlay": "172,962,607.48",
    "apollo": "340,341,937.41"
  },
  {
    "date": "2022-04-10",
    "starlay": "190,212,309.82",
    "apollo": "347,204,236.73"
  },
  {
    "date": "2022-04-11",
    "starlay": "199,574,148.09",
    "apollo": "343,573,354.11"
  },
  {
    "date": "2022-04-12",
    "starlay": "188,286,693.08",
    "apollo": "332,688,053.62"
  },
  {
    "date": "2022-04-13",
    "starlay": "188,942,838.64",
    "apollo": "335,274,498.34"
  },
  {
    "date": "2022-04-14",
    "starlay": "188,442,892.29",
    "apollo": "342,250,488.78"
  },
  {
    "date": "2022-04-15",
    "starlay": "183,237,978.70",
    "apollo": "338,920,712.37"
  },
  {
    "date": "2022-04-16",
    "starlay": "200,163,399.30",
    "apollo": "339,492,027.12"
  },
  {
    "date": "2022-04-17",
    "starlay": "194,606,156.91",
    "apollo": "341,493,013.96"
  },
  {
    "date": "2022-04-18",
    "starlay": "188,842,094.69",
    "apollo": "331,629,992.24"
  },
  {
    "date": "2022-04-19",
    "starlay": "193,538,470.68",
    "apollo": "336,319,704.38"
  },
  {
    "date": "2022-04-20",
    "starlay": "188,110,978.02",
    "apollo": "336,948,328.25"
  },
  {
    "date": "2022-04-21",
    "starlay": "186,236,007.10",
    "apollo": "330,328,798.12"
  },
  {
    "date": "2022-04-22",
    "starlay": "181,902,718.74",
    "apollo": "326,437,729.13"
  },
  {
    "date": "2022-04-23",
    "starlay": "176,627,700.29",
    "apollo": "331,041,999.47"
  },
  {
    "date": "2022-04-24",
    "starlay": "168,730,420.41",
    "apollo": "330,917,077.78"
  },
  {
    "date": "2022-04-25",
    "starlay": "157,405,790.78",
    "apollo": "324,917,538.56"
  },
  {
    "date": "2022-04-26",
    "starlay": "166,695,654.83",
    "apollo": "330,588,438.93"
  },
  {
    "date": "2022-04-27",
    "starlay": "156,771,446.76",
    "apollo": "318,037,266.63"
  },
  {
    "date": "2022-04-28",
    "starlay": "152,010,343.30",
    "apollo": "312,622,456.73"
  },
  {
    "date": "2022-04-29",
    "starlay": "154,642,395.84",
    "apollo": "315,814,254.32"
  },
  {
    "date": "2022-04-30",
    "starlay": "143,349,175.18",
    "apollo": "313,288,432.88"
  },
  {
    "date": "2022-05-01",
    "starlay": "138,440,660.77",
    "apollo": "303,017,627.68"
  },
  {
    "date": "2022-05-02",
    "starlay": "144,182,957.58",
    "apollo": "308,263,611.68"
  },
  {
    "date": "2022-05-03",
    "starlay": "146,476,669.13",
    "apollo": "309,576,368.60"
  },
  {
    "date": "2022-05-04",
    "starlay": "150,186,920.19",
    "apollo": "308,506,558.75"
  },
  {
    "date": "2022-05-05",
    "starlay": "157,096,136.14",
    "apollo": "315,403,876.26"
  },
  {
    "date": "2022-05-06",
    "starlay": "136,359,026.78",
    "apollo": "300,325,871.36"
  },
  {
    "date": "2022-05-07",
    "starlay": "137,948,199.47",
    "apollo": "293,904,210.51"
  },
  {
    "date": "2022-05-08",
    "starlay": "134,787,022.99",
    "apollo": "289,136,095.10"
  },
  {
    "date": "2022-05-09",
    "starlay": "129,543,239.03",
    "apollo": "278,524,935.45"
  },
  {
    "date": "2022-05-10",
    "starlay": "114,385,481.86",
    "apollo": "237,812,903.59"
  },
  {
    "date": "2022-05-11",
    "starlay": "116,423,599.27",
    "apollo": "239,772,584.02"
  },
  {
    "date": "2022-05-12",
    "starlay": "90,941,832.12",
    "apollo": "178,797,272.71"
  },
  {
    "date": "2022-05-13",
    "starlay": "78,706,874.13",
    "apollo": "158,169,019.53"
  },
  {
    "date": "2022-05-14",
    "starlay": "71,584,697.44",
    "apollo": "174,224,439.10"
  },
  {
    "date": "2022-05-15",
    "starlay": "70,451,028.73",
    "apollo": "175,715,014.87"
  },
  {
    "date": "2022-05-16",
    "starlay": "69,858,718.98",
    "apollo": "190,683,269.99"
  },
  {
    "date": "2022-05-17",
    "starlay": "59,146,775.68",
    "apollo": "185,399,279.85"
  },
  {
    "date": "2022-05-18",
    "starlay": "55,775,459.02",
    "apollo": "189,694,028.77"
  },
  {
    "date": "2022-05-19",
    "starlay": "52,561,628.67",
    "apollo": "192,407,550.78"
  },
  {
    "date": "2022-05-20",
    "starlay": "51,391,719.86",
    "apollo": "191,991,045.09"
  },
  {
    "date": "2022-05-21",
    "starlay": "52,351,708.90",
    "apollo": "190,848,739.88"
  },
  {
    "date": "2022-05-22",
    "starlay": "52,812,450.33",
    "apollo": "194,888,293.56"
  },
  {
    "date": "2022-05-23",
    "starlay": "53,327,084.47",
    "apollo": "197,193,691.43"
  },
  {
    "date": "2022-05-24",
    "starlay": "52,196,945.57",
    "apollo": "194,439,387.60"
  },
  {
    "date": "2022-05-25",
    "starlay": "53,147,281.71",
    "apollo": "199,720,397.10"
  },
  {
    "date": "2022-05-26",
    "starlay": "51,492,910.84",
    "apollo": "198,731,833.70"
  },
  {
    "date": "2022-05-27",
    "starlay": "46,661,483.69",
    "apollo": "194,541,797.72"
  },
  {
    "date": "2022-05-28",
    "starlay": "26,562,832.84",
    "apollo": "193,971,137.36"
  },
  {
    "date": "2022-05-29",
    "starlay": "26,458,034.68",
    "apollo": "195,191,797.54"
  },
  {
    "date": "2022-05-30",
    "starlay": "23,853,820.29",
    "apollo": "193,218,147.96"
  },
  {
    "date": "2022-05-31",
    "starlay": "18,595,302.18",
    "apollo": "198,867,677.06"
  },
  {
    "date": "2022-06-01",
    "starlay": "17,075,601.25",
    "apollo": "196,978,187.88"
  },
  {
    "date": "2022-06-02",
    "starlay": "19,584,704.76",
    "apollo": "185,311,813.38"
  },
  {
    "date": "2022-06-03",
    "starlay": "21,311,782.76",
    "apollo": "185,956,225.47"
  },
  {
    "date": "2022-06-04",
    "starlay": "21,626,231.25",
    "apollo": "175,659,312.20"
  },
  {
    "date": "2022-06-05",
    "starlay": "22,561,765.53",
    "apollo": "176,884,127.47"
  },
  {
    "date": "2022-06-06",
    "starlay": "22,652,261.36",
    "apollo": "178,884,822.73"
  },
  {
    "date": "2022-06-07",
    "starlay": "21,114,111.79",
    "apollo": "168,472,212.92"
  },
  {
    "date": "2022-06-08",
    "starlay": "21,584,688.38",
    "apollo": "169,752,267.51"
  },
  {
    "date": "2022-06-09",
    "starlay": "20,528,873.93",
    "apollo": "168,971,652.91"
  },
  {
    "date": "2022-06-10",
    "starlay": "20,473,409.62",
    "apollo": "168,546,078.27"
  },
  {
    "date": "2022-06-11",
    "starlay": "19,238,631.86",
    "apollo": "162,848,474.73"
  },
  {
    "date": "2022-06-12",
    "starlay": "18,803,451.38",
    "apollo": "155,930,535.94"
  },
  {
    "date": "2022-06-13",
    "starlay": "18,239,257.72",
    "apollo": "148,606,350.27"
  },
  {
    "date": "2022-06-14",
    "starlay": "16,910,856.32",
    "apollo": "137,969,985.14"
  },
  {
    "date": "2022-06-15",
    "starlay": "16,925,776.31",
    "apollo": "129,994,779.03"
  },
  {
    "date": "2022-06-16",
    "starlay": "17,774,946.02",
    "apollo": "126,609,835.45"
  },
  {
    "date": "2022-06-17",
    "starlay": "16,607,218.25",
    "apollo": "115,220,206.98"
  },
  {
    "date": "2022-06-18",
    "starlay": "15,907,480.51",
    "apollo": "108,090,720.38"
  },
  {
    "date": "2022-06-19",
    "starlay": "14,991,668.41",
    "apollo": "93,407,386.78"
  },
  {
    "date": "2022-06-20",
    "starlay": "15,640,753.69",
    "apollo": "94,664,824.33"
  },
  {
    "date": "2022-06-21",
    "starlay": "15,758,351.61",
    "apollo": "97,500,181.77"
  },
  {
    "date": "2022-06-22",
    "starlay": "15,176,057.01",
    "apollo": "97,253,234.14"
  },
  {
    "date": "2022-06-23",
    "starlay": "14,946,575.23",
    "apollo": "81,889,012.99"
  },
  {
    "date": "2022-06-24",
    "starlay": "14,996,744.02",
    "artemis": "143,577,607.56",
    "apollo": "190,044,539.38"
  },
  {
    "date": "2022-06-25",
    "starlay": "15,734,711.95",
    "artemis": "166,511,846.17",
    "apollo": "87,949,004.19"
  },
  {
    "date": "2022-06-26",
    "starlay": "15,826,450.03",
    "artemis": "172,919,926.94",
    "apollo": "88,105,564.63"
  },
  {
    "date": "2022-06-27",
    "starlay": "15,970,515.11",
    "artemis": "175,607,481.60",
    "apollo": "89,067,966.85"
  },
  {
    "date": "2022-06-28",
    "starlay": "17,940,245.15",
    "artemis": "179,887,297.58",
    "apollo": "90,441,435.42"
  },
  {
    "date": "2022-06-29",
    "starlay": "14,264,654.81",
    "artemis": "174,225,727.91",
    "apollo": "92,258,503.44"
  },
  {
    "date": "2022-06-30",
    "starlay": "13,406,760.82",
    "artemis": "176,132,377.07",
    "apollo": "91,821,958.00"
  }
]
